xrdmon-0.1.dev3.dist-info/DESCRIPTION.rst
xrdmon-0.1.dev3.dist-info/METADATA
xrdmon-0.1.dev3.dist-info/RECORD
xrdmon-0.1.dev3.dist-info/WHEEL
xrdmon-0.1.dev3.dist-info/entry_points.txt
xrdmon-0.1.dev3.dist-info/metadata.json
xrdmon-0.1.dev3.dist-info/top_level.txt
xrdmonlib/__about__.py
xrdmonlib/__init__.py
xrdmonlib/core.py
xrdmonlib/interface.py
xrdmonlib/utils.py
xrdmonlib/xrdreports.py
xrdmonlib/backend/__init__.py
xrdmonlib/backend/apmon.py
xrdmonlib/backend/base.py
xrdmonlib/backend/filepath.py
xrdmonlib/backend/transform.py
xrdmonlib/compat/__init__.py
xrdmonlib/compat/_runpy.py
